dynamics_engine/__init__.py
dynamics_engine/config.py
dynamics_engine/dynamics_engine.py
dynamics_engine/models.py
dynamics_engine-1.0.0.dist-info/licenses/LICENSE
dynamics_engine-1.0.0.dist-info/METADATA
dynamics_engine-1.0.0.dist-info/WHEEL
dynamics_engine-1.0.0.dist-info/top_level.txt
dynamics_engine-1.0.0.dist-info/RECORD
