Metadata-Version: 2.4
Name: dynamics-engine
Version: 1.0.0
Summary: Cognitive Dynamics Engine - Entropy, Core Strength, Rotational Torque
Home-page: https://github.com/gnjz/dynamics-engine
Author: GNJz (Qquarts)
Author-email: 
Project-URL: Documentation, https://github.com/gnjz/dynamics-engine#readme
Project-URL: Source, https://github.com/gnjz/dynamics-engine
Project-URL: Tracker, https://github.com/gnjz/dynamics-engine/issues
Keywords: cognitive,dynamics,entropy,core-strength,torque,ai,edge-ai,neuroscience,cognitive-modeling
Classifier: Development Status :: 4 - Beta
Classifier: Intended Audience :: Developers
Classifier: Intended Audience :: Science/Research
Classifier: License :: OSI Approved :: MIT License
Classifier: Programming Language :: Python :: 3
Classifier: Programming Language :: Python :: 3.8
Classifier: Programming Language :: Python :: 3.9
Classifier: Programming Language :: Python :: 3.10
Classifier: Programming Language :: Python :: 3.11
Classifier: Topic :: Scientific/Engineering :: Artificial Intelligence
Classifier: Topic :: Software Development :: Libraries :: Python Modules
Requires-Python: >=3.8
License-File: LICENSE
Provides-Extra: dev
Requires-Dist: pytest>=7.0.0; extra == "dev"
Requires-Dist: pytest-cov>=4.0.0; extra == "dev"
Requires-Dist: black>=23.0.0; extra == "dev"
Requires-Dist: mypy>=1.0.0; extra == "dev"
Dynamic: author
Dynamic: classifier
Dynamic: description
Dynamic: description-content-type
Dynamic: home-page
Dynamic: keywords
Dynamic: license-file
Dynamic: project-url
Dynamic: provides-extra
Dynamic: requires-python
Dynamic: summary
